setup.py
ferb_uda/Binomialdistribution.py
ferb_uda/Gaussiandistribution.py
ferb_uda/Generaldistribution.py
ferb_uda/__init__.py
ferb_uda.egg-info/PKG-INFO
ferb_uda.egg-info/SOURCES.txt
ferb_uda.egg-info/dependency_links.txt
ferb_uda.egg-info/not-zip-safe
ferb_uda.egg-info/top_level.txt